pyaadhaar/__init__.py
pyaadhaar/decode.py
pyaadhaar/test.py
pyaadhaar/utils.py
pyaadhaar-2.0.1.dist-info/METADATA
pyaadhaar-2.0.1.dist-info/WHEEL
pyaadhaar-2.0.1.dist-info/top_level.txt
pyaadhaar-2.0.1.dist-info/RECORD
