Metadata-Version: 2.1
Name: pyaadhaar
Version: 2.0.1
Summary: This library is built to ease the process of decoding aadhaar QR codes and XML. It supprts old aadhaar QR codes , newly released Secure aadhaar QR codes and also Offline e-KYC XML. This library also can decode QR codes with Opncv. This library bundled with all the features to verify user's Email Id and Mobile Number & also to extract the photo of user. 
Home-page: https://github.com/Tanmoy741127/pyaadhaar
Author: Tanmoy Sarkar
Author-email: ts741127@gmail.com
License: MIT
Keywords: software development aadhaar e-kyc verification
Classifier: Development Status :: 4 - Beta
Classifier: Intended Audience :: Developers 
Classifier: Topic :: Software Development :: Libraries :: Python Modules
Classifier: License :: OSI Approved :: MIT License
Classifier: Programming Language :: Python :: 3.8
Requires-Python: >=3.6
Requires-Dist: numpy
Requires-Dist: opencv-python
Requires-Dist: Pillow
Requires-Dist: pylibjpeg
Requires-Dist: pylibjpeg-openjpeg
Requires-Dist: python-dateutil
Requires-Dist: pytz
Requires-Dist: pyzbar
Requires-Dist: six
Requires-Dist: toml
